Fixie/Constants.py
Fixie/Parser.py
Fixie/Protocol.py
Fixie/Tags.py
Fixie/Types.py
Fixie/__init__.py
Fixie/Tools/FixToJson.py
Fixie/Tools/GenerateTagMappings.py
Fixie/Tools/ViewFix.py
Fixie/Tools/__init__.py
PyFixie-0.0.3.dist-info/LICENSE
PyFixie-0.0.3.dist-info/METADATA
PyFixie-0.0.3.dist-info/WHEEL
PyFixie-0.0.3.dist-info/top_level.txt
PyFixie-0.0.3.dist-info/RECORD
